nafigator/__init__.py
nafigator/cli.py
nafigator/const.py
nafigator/linguisticprocessor.py
nafigator/nafdocument.py
nafigator/ocrprocessor.py
nafigator/parse2naf.py
nafigator/preprocessprocessor.py
nafigator/term_extraction.py
nafigator/termbaseprocessor.py
nafigator/utils.py
nafigator/postprocessor/__init__.py
nafigator/postprocessor/highlighter.py
nafigator/postprocessor/tableformatter.py
nafigator-0.1.64.dist-info/AUTHORS.rst
nafigator-0.1.64.dist-info/LICENSE
nafigator-0.1.64.dist-info/METADATA
nafigator-0.1.64.dist-info/WHEEL
nafigator-0.1.64.dist-info/entry_points.txt
nafigator-0.1.64.dist-info/top_level.txt
nafigator-0.1.64.dist-info/RECORD
