Metadata-Version: 2.1
Name: nafigator
Version: 0.1.64
Summary: Python package to convert spaCy and Stanza documents to NLP Annotation Format (NAF)
Home-page: https://github.com/denederlandschebank/nafigator
Author: De Nederlandsche Bank
Author-email: w.j.willemse@dnb.nl
License: MIT license
Keywords: nafigator
Platform: UNKNOWN
Classifier: Development Status :: 2 - Pre-Alpha
Classifier: Intended Audience :: Developers
Classifier: License :: OSI Approved :: MIT License
Classifier: Natural Language :: English
Classifier: Programming Language :: Python :: 3
Classifier: Programming Language :: Python :: 3.6
Classifier: Programming Language :: Python :: 3.7
Classifier: Programming Language :: Python :: 3.8
Classifier: Programming Language :: Python :: 3.9
Requires-Python: >=3.6
License-File: LICENSE
License-File: AUTHORS.rst
Requires-Dist: click (>=7.0)
Requires-Dist: pdfminer.six (>=20200726)
Requires-Dist: lxml
Requires-Dist: python-docx
Requires-Dist: folia
Requires-Dist: pandas
Requires-Dist: camelot-py (>=0.10.1)
Requires-Dist: opencv-python (==4.7.0.68)
Requires-Dist: pdftopng (==0.2.3)
Requires-Dist: iribaker (==0.2)
Requires-Dist: Unidecode (==1.3.6)
Requires-Dist: PyMuPDF (==1.21.0)
